odoo/addons/sale_automatic_workflow_order_type/README.rst
odoo/addons/sale_automatic_workflow_order_type/__init__.py
odoo/addons/sale_automatic_workflow_order_type/__manifest__.py
odoo/addons/sale_automatic_workflow_order_type/i18n/es.po
odoo/addons/sale_automatic_workflow_order_type/models/__init__.py
odoo/addons/sale_automatic_workflow_order_type/models/sale_order.py
odoo/addons/sale_automatic_workflow_order_type/models/sale_order_type.py
odoo/addons/sale_automatic_workflow_order_type/readme/CONFIGURE.md
odoo/addons/sale_automatic_workflow_order_type/readme/CONTRIBUTORS.md
odoo/addons/sale_automatic_workflow_order_type/readme/DESCRIPTION.md
odoo/addons/sale_automatic_workflow_order_type/readme/USAGE.md
odoo/addons/sale_automatic_workflow_order_type/static/description/icon.png
odoo/addons/sale_automatic_workflow_order_type/static/description/index.html
odoo/addons/sale_automatic_workflow_order_type/tests/__init__.py
odoo/addons/sale_automatic_workflow_order_type/tests/test_sale_automatic_workflow_order_type.py
odoo/addons/sale_automatic_workflow_order_type/views/sale_order_type_view.xml
odoo_addon_sale_automatic_workflow_order_type-17.0.1.0.0.1.dist-info/METADATA
odoo_addon_sale_automatic_workflow_order_type-17.0.1.0.0.1.dist-info/WHEEL
odoo_addon_sale_automatic_workflow_order_type-17.0.1.0.0.1.dist-info/top_level.txt
odoo_addon_sale_automatic_workflow_order_type-17.0.1.0.0.1.dist-info/RECORD
